pyjavapoet/__init__.py
pyjavapoet/annotation_spec.py
pyjavapoet/code_base.py
pyjavapoet/code_block.py
pyjavapoet/code_writer.py
pyjavapoet/field_spec.py
pyjavapoet/java_file.py
pyjavapoet/method_spec.py
pyjavapoet/modifier.py
pyjavapoet/parameter_spec.py
pyjavapoet/type_name.py
pyjavapoet/type_spec.py
pyjavapoet/util.py
pyjavapoet-0.1.4.dist-info/licenses/LICENSE
pyjavapoet-0.1.4.dist-info/METADATA
pyjavapoet-0.1.4.dist-info/WHEEL
pyjavapoet-0.1.4.dist-info/top_level.txt
pyjavapoet-0.1.4.dist-info/RECORD
