Metadata-Version: 2.4
Name: pyjavapoet
Version: 0.1.4
Summary: A Python API for generating Java source files
Author-email: Matthew Au-Yeung <matthewauyeung04@gmail.com>
Project-URL: Homepage, https://github.com/m4tth3/pyjavapoet
Requires-Python: >=3.12
License-File: LICENSE
Dynamic: license-file
